{
  "level": "beginner",
  "definitions": [
    {
      "word": "happy",
      "definition": "feeling joy or pleasure"
    },
    {
      "word": "heavy",
      "definition": "having great weight; difficult to lift"
    },
    {
      "word": "open",
      "definition": "not closed; to make accessible"
    },
    {
      "word": "big",
      "definition": "large in size or amount"
    },
    {
      "word": "cook",
      "definition": "to prepare food by heating"
    },
    {
      "word": "hot",
      "definition": "having high temperature"
    },
    {
      "word": "study",
      "definition": "to learn about something carefully"
    },
    {
      "word": "small",
      "definition": "little in size"
    },
    {
      "word": "live",
      "definition": "to have life; to reside somewhere"
    },
    {
      "word": "quiet",
      "definition": "making little or no noise"
    }
  ]
}
